api/__init__.py
api/accesscontrolprofile.py
api/accesstoken.py
api/apierror.py
api/apiobject.py
api/batch.py
api/branch.py
api/branchupdate.py
api/changeset.py
api/comment.py
api/commit.py
api/commitset.py
api/config.py
api/critic.py
api/extension.py
api/file.py
api/filechange.py
api/filecontent.py
api/filediff.py
api/filters.py
api/labeledaccesscontrolprofile.py
api/preference.py
api/reply.py
api/repository.py
api/review.py
api/reviewablefilechange.py
api/reviewsummary.py
api/systemsetting.py
api/user.py
api/impl/__init__.py
api/impl/accesscontrolprofile.py
api/impl/accesstoken.py
api/impl/apiobject.py
api/impl/batch.py
api/impl/branch.py
api/impl/branch_unittest.py
api/impl/branchupdate.py
api/impl/branchupdate_unittest.py
api/impl/changeset.py
api/impl/changeset_unittest.py
api/impl/comment.py
api/impl/comment_unittest.py
api/impl/commit.py
api/impl/commit_unittest.py
api/impl/commitset.py
api/impl/commitset_unittest.py
api/impl/config_unittest.py
api/impl/critic.py
api/impl/extension.py
api/impl/file.py
api/impl/filechange.py
api/impl/filechange_unittest.py
api/impl/filecontent.py
api/impl/filediff.py
api/impl/filediff_unittest.py
api/impl/filters.py
api/impl/labeledaccesscontrolprofile.py
api/impl/reply.py
api/impl/reply_unittest.py
api/impl/repository.py
api/impl/repository_unittest.py
api/impl/review.py
api/impl/review_unittest.py
api/impl/reviewablefilechange.py
api/impl/reviewsummary.py
api/impl/systemsetting.py
api/impl/user.py
api/impl/user_unittest.py
api/impl/log/__init__.py
api/impl/log/partition.py
api/impl/log/partition_unittest.py
api/impl/log/rebase.py
api/impl/log/rebase_unittest.py
api/log/__init__.py
api/log/partition.py
api/log/rebase.py
api/transaction/__init__.py
api/transaction/accesscontrolprofile.py
api/transaction/accesstoken.py
api/transaction/comment.py
api/transaction/filters.py
api/transaction/labeledaccesscontrolprofile.py
api/transaction/reply.py
critic_review-2.0.1.dist-info/DESCRIPTION.rst
critic_review-2.0.1.dist-info/METADATA
critic_review-2.0.1.dist-info/RECORD
critic_review-2.0.1.dist-info/WHEEL
critic_review-2.0.1.dist-info/entry_points.txt
critic_review-2.0.1.dist-info/metadata.json
critic_review-2.0.1.dist-info/top_level.txt
critic_review-2.0.1.dist-info/zip-safe
