Metadata-Version: 2.0
Name: critic-review
Version: 2.0.1
Summary: The Critic code review system
Home-page: https://critic-review.org/
Author: The Critic contributors
Author-email: critic-dev@critic-review.org
License: Apache License, Version 2.0
Platform: UNKNOWN
Classifier: Development Status :: 4 - Beta
Classifier: Intended Audience :: Developers
Classifier: Topic :: Software Development :: Version Control
Classifier: Operating System :: POSIX :: Linux
Classifier: Programming Language :: Python :: 3.6
Requires-Python: ~=3.6
Requires-Dist: argon2-cffi
Requires-Dist: passlib
Requires-Dist: psycopg2
Requires-Dist: pygments
Requires-Dist: requests
